demo_reader/__init__.py
demo_reader/multireader.py
demo_reader/compressed/__init__.py
demo_reader/compressed/bzipped.py
demo_reader/compressed/gzipped.py
demo_reader/util/__init__.py
demo_reader/util/writer.py
smarlaku_pyreader-1.0.0.dist-info/DESCRIPTION.rst
smarlaku_pyreader-1.0.0.dist-info/METADATA
smarlaku_pyreader-1.0.0.dist-info/RECORD
smarlaku_pyreader-1.0.0.dist-info/WHEEL
smarlaku_pyreader-1.0.0.dist-info/metadata.json
smarlaku_pyreader-1.0.0.dist-info/top_level.txt
