Metadata-Version: 2.0
Name: smarlaku-pyreader
Version: 1.0.0
Summary: Tools for reading various file formats
Home-page: UNKNOWN
Author: UNKNOWN
Author-email: UNKNOWN
License: UNKNOWN
Platform: UNKNOWN
